openseestcl2py/__init__.py
openseestcl2py/convert.py
openseestcl2py/utilities.py
OpenSeesTcl2Py-0.0.1.dist-info/LICENSE
OpenSeesTcl2Py-0.0.1.dist-info/METADATA
OpenSeesTcl2Py-0.0.1.dist-info/WHEEL
OpenSeesTcl2Py-0.0.1.dist-info/top_level.txt
OpenSeesTcl2Py-0.0.1.dist-info/RECORD
