Metadata-Version: 2.1
Name: OpenSeesTcl2Py
Version: 0.0.1
Summary: An OpenSeesTcl file converter to OpenSeespy
Author-email: Konstantinos Mixios <k.mixios@gmail.com>
Project-URL: Homepage, http://mixiosk.com
Project-URL: Bug Tracker, https://github.com/iammix/OpenSeesTcl2Py/issues
Classifier: Programming Language :: Python :: 3
Classifier: License :: OSI Approved :: MIT License
Classifier: Operating System :: OS Independent
Requires-Python: >=3.7
License-File: LICENSE
